setup.py
hualang/__init__.py
hualang.egg-info/PKG-INFO
hualang.egg-info/SOURCES.txt
hualang.egg-info/dependency_links.txt
hualang.egg-info/entry_points.txt
hualang.egg-info/not-zip-safe
hualang.egg-info/top_level.txt