Metadata-Version: 1.0
Name: hualang
Version: 2020.4.25.1618
Summary: make a Markdown table of images at the working directory
Home-page: https://github.com/wdbm/hualang
Author: Will Breaden Madden
Author-email: wbm@protonmail.ch
License: GPLv3
Platform: UNKNOWN
